flask_on_fhir/__init__.py
flask_on_fhir/core.py
flask_on_fhir/decorator.py
flask_on_fhir/extension.py
flask_on_fhir/resources/__init__.py
flask_on_fhir/resources/capability_statement.py
flask_on_fhir/resources/code_system.py
flask_on_fhir/resources/fhir_resource.py
Flask_on_FHIR-0.0.1.dev0.dist-info/LICENSE
Flask_on_FHIR-0.0.1.dev0.dist-info/METADATA
Flask_on_FHIR-0.0.1.dev0.dist-info/WHEEL
Flask_on_FHIR-0.0.1.dev0.dist-info/top_level.txt
Flask_on_FHIR-0.0.1.dev0.dist-info/RECORD
