Metadata-Version: 2.1
Name: Flask-on-FHIR
Version: 0.0.1.dev0
Summary: A FLASK extension to for building FHIR RESTful API
Home-page: http://github.com/jiaola/flask-on-fhir
Author: Dazhi Jiao
Author-email: djiao@jhu.edu
License: BSD
Platform: any
Classifier: Environment :: Web Environment
Classifier: Intended Audience :: Developers
Classifier: License :: OSI Approved :: BSD License
Classifier: Operating System :: OS Independent
Classifier: Programming Language :: Python
Classifier: Topic :: Internet :: WWW/HTTP :: Dynamic Content
Classifier: Topic :: Software Development :: Libraries :: Python Modules
Requires-Python: >=3.6
Requires-Dist: Flask
